<stg><name>concatenate3d<array,array,array<ap_fixed<16,6,5,3,0>,6u>,config13></name>


<trans_list>

<trans id="39" from="1" to="2">
<condition id="-1">
<or_exp><and_exp></and_exp></or_exp>
</condition>
</trans>

<trans id="45" from="2" to="4">
<condition id="-1">
<or_exp><and_exp><literal name="icmp_ln232" val="1"/>
</and_exp></or_exp>
</condition>
</trans>

<trans id="46" from="2" to="3">
<condition id="-1">
<or_exp><and_exp><literal name="icmp_ln232" val="0"/>
</and_exp></or_exp>
</condition>
</trans>

<trans id="44" from="3" to="2">
<condition id="-1">
<or_exp><and_exp></and_exp></or_exp>
</condition>
</trans>
</trans_list>



<state_list>

<state id="1" st_id="1">

<operation id="5" st_id="1" stage="1" lat="1">
<core>NULL</core>
<MemPortIdVec></MemPortIdVec>
<condition id="-1">
<or_exp><and_exp></and_exp></or_exp>
</condition>

<Node id="13" bw="0" op_0_bw="0" op_1_bw="16" op_2_bw="0" op_3_bw="32" op_4_bw="32" op_5_bw="0" op_6_bw="32" op_7_bw="32" op_8_bw="0" op_9_bw="0" op_10_bw="0" op_11_bw="32" op_12_bw="32" op_13_bw="32" op_14_bw="32" op_15_bw="0" op_16_bw="0">
<![CDATA[
:0  call void (...)* @_ssdm_op_SpecInterface(i16* %res_V_data_5_V, [8 x i8]* @ap_fifo_str, i32 0, i32 0, [1 x i8]* @p_str, i32 0, i32 0, [1 x i8]* @p_str, [1 x i8]* @p_str, [1 x i8]* @p_str, i32 2, i32 2, i32 16, i32 16, [1 x i8]* @p_str, [1 x i8]* @p_str)

]]></Node>
<StgValue><ssdm name="specinterface_ln0"/></StgValue>
</operation>

<operation id="6" st_id="1" stage="1" lat="1">
<core>NULL</core>
<MemPortIdVec></MemPortIdVec>
<condition id="-1">
<or_exp><and_exp></and_exp></or_exp>
</condition>

<Node id="14" bw="0" op_0_bw="0" op_1_bw="16" op_2_bw="0" op_3_bw="32" op_4_bw="32" op_5_bw="0" op_6_bw="32" op_7_bw="32" op_8_bw="0" op_9_bw="0" op_10_bw="0" op_11_bw="32" op_12_bw="32" op_13_bw="32" op_14_bw="32" op_15_bw="0" op_16_bw="0">
<![CDATA[
:1  call void (...)* @_ssdm_op_SpecInterface(i16* %res_V_data_4_V, [8 x i8]* @ap_fifo_str, i32 0, i32 0, [1 x i8]* @p_str, i32 0, i32 0, [1 x i8]* @p_str, [1 x i8]* @p_str, [1 x i8]* @p_str, i32 2, i32 2, i32 16, i32 16, [1 x i8]* @p_str, [1 x i8]* @p_str)

]]></Node>
<StgValue><ssdm name="specinterface_ln0"/></StgValue>
</operation>

<operation id="7" st_id="1" stage="1" lat="1">
<core>NULL</core>
<MemPortIdVec></MemPortIdVec>
<condition id="-1">
<or_exp><and_exp></and_exp></or_exp>
</condition>

<Node id="15" bw="0" op_0_bw="0" op_1_bw="16" op_2_bw="0" op_3_bw="32" op_4_bw="32" op_5_bw="0" op_6_bw="32" op_7_bw="32" op_8_bw="0" op_9_bw="0" op_10_bw="0" op_11_bw="32" op_12_bw="32" op_13_bw="32" op_14_bw="32" op_15_bw="0" op_16_bw="0">
<![CDATA[
:2  call void (...)* @_ssdm_op_SpecInterface(i16* %res_V_data_3_V, [8 x i8]* @ap_fifo_str, i32 0, i32 0, [1 x i8]* @p_str, i32 0, i32 0, [1 x i8]* @p_str, [1 x i8]* @p_str, [1 x i8]* @p_str, i32 2, i32 2, i32 16, i32 16, [1 x i8]* @p_str, [1 x i8]* @p_str)

]]></Node>
<StgValue><ssdm name="specinterface_ln0"/></StgValue>
</operation>

<operation id="8" st_id="1" stage="1" lat="1">
<core>NULL</core>
<MemPortIdVec></MemPortIdVec>
<condition id="-1">
<or_exp><and_exp></and_exp></or_exp>
</condition>

<Node id="16" bw="0" op_0_bw="0" op_1_bw="16" op_2_bw="0" op_3_bw="32" op_4_bw="32" op_5_bw="0" op_6_bw="32" op_7_bw="32" op_8_bw="0" op_9_bw="0" op_10_bw="0" op_11_bw="32" op_12_bw="32" op_13_bw="32" op_14_bw="32" op_15_bw="0" op_16_bw="0">
<![CDATA[
:3  call void (...)* @_ssdm_op_SpecInterface(i16* %res_V_data_2_V, [8 x i8]* @ap_fifo_str, i32 0, i32 0, [1 x i8]* @p_str, i32 0, i32 0, [1 x i8]* @p_str, [1 x i8]* @p_str, [1 x i8]* @p_str, i32 2, i32 2, i32 16, i32 16, [1 x i8]* @p_str, [1 x i8]* @p_str)

]]></Node>
<StgValue><ssdm name="specinterface_ln0"/></StgValue>
</operation>

<operation id="9" st_id="1" stage="1" lat="1">
<core>NULL</core>
<MemPortIdVec></MemPortIdVec>
<condition id="-1">
<or_exp><and_exp></and_exp></or_exp>
</condition>

<Node id="17" bw="0" op_0_bw="0" op_1_bw="16" op_2_bw="0" op_3_bw="32" op_4_bw="32" op_5_bw="0" op_6_bw="32" op_7_bw="32" op_8_bw="0" op_9_bw="0" op_10_bw="0" op_11_bw="32" op_12_bw="32" op_13_bw="32" op_14_bw="32" op_15_bw="0" op_16_bw="0">
<![CDATA[
:4  call void (...)* @_ssdm_op_SpecInterface(i16* %res_V_data_1_V, [8 x i8]* @ap_fifo_str, i32 0, i32 0, [1 x i8]* @p_str, i32 0, i32 0, [1 x i8]* @p_str, [1 x i8]* @p_str, [1 x i8]* @p_str, i32 2, i32 2, i32 16, i32 16, [1 x i8]* @p_str, [1 x i8]* @p_str)

]]></Node>
<StgValue><ssdm name="specinterface_ln0"/></StgValue>
</operation>

<operation id="10" st_id="1" stage="1" lat="1">
<core>NULL</core>
<MemPortIdVec></MemPortIdVec>
<condition id="-1">
<or_exp><and_exp></and_exp></or_exp>
</condition>

<Node id="18" bw="0" op_0_bw="0" op_1_bw="16" op_2_bw="0" op_3_bw="32" op_4_bw="32" op_5_bw="0" op_6_bw="32" op_7_bw="32" op_8_bw="0" op_9_bw="0" op_10_bw="0" op_11_bw="32" op_12_bw="32" op_13_bw="32" op_14_bw="32" op_15_bw="0" op_16_bw="0">
<![CDATA[
:5  call void (...)* @_ssdm_op_SpecInterface(i16* %res_V_data_0_V, [8 x i8]* @ap_fifo_str, i32 0, i32 0, [1 x i8]* @p_str, i32 0, i32 0, [1 x i8]* @p_str, [1 x i8]* @p_str, [1 x i8]* @p_str, i32 2, i32 2, i32 16, i32 16, [1 x i8]* @p_str, [1 x i8]* @p_str)

]]></Node>
<StgValue><ssdm name="specinterface_ln0"/></StgValue>
</operation>

<operation id="11" st_id="1" stage="1" lat="1">
<core>NULL</core>
<MemPortIdVec></MemPortIdVec>
<condition id="-1">
<or_exp><and_exp></and_exp></or_exp>
</condition>

<Node id="19" bw="0" op_0_bw="0" op_1_bw="16" op_2_bw="0" op_3_bw="32" op_4_bw="32" op_5_bw="0" op_6_bw="32" op_7_bw="32" op_8_bw="0" op_9_bw="0" op_10_bw="0" op_11_bw="32" op_12_bw="32" op_13_bw="32" op_14_bw="32" op_15_bw="0" op_16_bw="0">
<![CDATA[
:6  call void (...)* @_ssdm_op_SpecInterface(i16* %data2_V_data_2_V, [8 x i8]* @ap_fifo_str, i32 0, i32 0, [1 x i8]* @p_str, i32 0, i32 0, [1 x i8]* @p_str, [1 x i8]* @p_str, [1 x i8]* @p_str, i32 2, i32 2, i32 16, i32 16, [1 x i8]* @p_str, [1 x i8]* @p_str)

]]></Node>
<StgValue><ssdm name="specinterface_ln0"/></StgValue>
</operation>

<operation id="12" st_id="1" stage="1" lat="1">
<core>NULL</core>
<MemPortIdVec></MemPortIdVec>
<condition id="-1">
<or_exp><and_exp></and_exp></or_exp>
</condition>

<Node id="20" bw="0" op_0_bw="0" op_1_bw="16" op_2_bw="0" op_3_bw="32" op_4_bw="32" op_5_bw="0" op_6_bw="32" op_7_bw="32" op_8_bw="0" op_9_bw="0" op_10_bw="0" op_11_bw="32" op_12_bw="32" op_13_bw="32" op_14_bw="32" op_15_bw="0" op_16_bw="0">
<![CDATA[
:7  call void (...)* @_ssdm_op_SpecInterface(i16* %data2_V_data_1_V, [8 x i8]* @ap_fifo_str, i32 0, i32 0, [1 x i8]* @p_str, i32 0, i32 0, [1 x i8]* @p_str, [1 x i8]* @p_str, [1 x i8]* @p_str, i32 2, i32 2, i32 16, i32 16, [1 x i8]* @p_str, [1 x i8]* @p_str)

]]></Node>
<StgValue><ssdm name="specinterface_ln0"/></StgValue>
</operation>

<operation id="13" st_id="1" stage="1" lat="1">
<core>NULL</core>
<MemPortIdVec></MemPortIdVec>
<condition id="-1">
<or_exp><and_exp></and_exp></or_exp>
</condition>

<Node id="21" bw="0" op_0_bw="0" op_1_bw="16" op_2_bw="0" op_3_bw="32" op_4_bw="32" op_5_bw="0" op_6_bw="32" op_7_bw="32" op_8_bw="0" op_9_bw="0" op_10_bw="0" op_11_bw="32" op_12_bw="32" op_13_bw="32" op_14_bw="32" op_15_bw="0" op_16_bw="0">
<![CDATA[
:8  call void (...)* @_ssdm_op_SpecInterface(i16* %data2_V_data_0_V, [8 x i8]* @ap_fifo_str, i32 0, i32 0, [1 x i8]* @p_str, i32 0, i32 0, [1 x i8]* @p_str, [1 x i8]* @p_str, [1 x i8]* @p_str, i32 2, i32 2, i32 16, i32 16, [1 x i8]* @p_str, [1 x i8]* @p_str)

]]></Node>
<StgValue><ssdm name="specinterface_ln0"/></StgValue>
</operation>

<operation id="14" st_id="1" stage="1" lat="1">
<core>NULL</core>
<MemPortIdVec></MemPortIdVec>
<condition id="-1">
<or_exp><and_exp></and_exp></or_exp>
</condition>

<Node id="22" bw="0" op_0_bw="0" op_1_bw="16" op_2_bw="0" op_3_bw="32" op_4_bw="32" op_5_bw="0" op_6_bw="32" op_7_bw="32" op_8_bw="0" op_9_bw="0" op_10_bw="0" op_11_bw="32" op_12_bw="32" op_13_bw="32" op_14_bw="32" op_15_bw="0" op_16_bw="0">
<![CDATA[
:9  call void (...)* @_ssdm_op_SpecInterface(i16* %data1_V_data_2_V, [8 x i8]* @ap_fifo_str, i32 0, i32 0, [1 x i8]* @p_str, i32 0, i32 0, [1 x i8]* @p_str, [1 x i8]* @p_str, [1 x i8]* @p_str, i32 2, i32 2, i32 16, i32 16, [1 x i8]* @p_str, [1 x i8]* @p_str)

]]></Node>
<StgValue><ssdm name="specinterface_ln0"/></StgValue>
</operation>

<operation id="15" st_id="1" stage="1" lat="1">
<core>NULL</core>
<MemPortIdVec></MemPortIdVec>
<condition id="-1">
<or_exp><and_exp></and_exp></or_exp>
</condition>

<Node id="23" bw="0" op_0_bw="0" op_1_bw="16" op_2_bw="0" op_3_bw="32" op_4_bw="32" op_5_bw="0" op_6_bw="32" op_7_bw="32" op_8_bw="0" op_9_bw="0" op_10_bw="0" op_11_bw="32" op_12_bw="32" op_13_bw="32" op_14_bw="32" op_15_bw="0" op_16_bw="0">
<![CDATA[
:10  call void (...)* @_ssdm_op_SpecInterface(i16* %data1_V_data_1_V, [8 x i8]* @ap_fifo_str, i32 0, i32 0, [1 x i8]* @p_str, i32 0, i32 0, [1 x i8]* @p_str, [1 x i8]* @p_str, [1 x i8]* @p_str, i32 2, i32 2, i32 16, i32 16, [1 x i8]* @p_str, [1 x i8]* @p_str)

]]></Node>
<StgValue><ssdm name="specinterface_ln0"/></StgValue>
</operation>

<operation id="16" st_id="1" stage="1" lat="1">
<core>NULL</core>
<MemPortIdVec></MemPortIdVec>
<condition id="-1">
<or_exp><and_exp></and_exp></or_exp>
</condition>

<Node id="24" bw="0" op_0_bw="0" op_1_bw="16" op_2_bw="0" op_3_bw="32" op_4_bw="32" op_5_bw="0" op_6_bw="32" op_7_bw="32" op_8_bw="0" op_9_bw="0" op_10_bw="0" op_11_bw="32" op_12_bw="32" op_13_bw="32" op_14_bw="32" op_15_bw="0" op_16_bw="0">
<![CDATA[
:11  call void (...)* @_ssdm_op_SpecInterface(i16* %data1_V_data_0_V, [8 x i8]* @ap_fifo_str, i32 0, i32 0, [1 x i8]* @p_str, i32 0, i32 0, [1 x i8]* @p_str, [1 x i8]* @p_str, [1 x i8]* @p_str, i32 2, i32 2, i32 16, i32 16, [1 x i8]* @p_str, [1 x i8]* @p_str)

]]></Node>
<StgValue><ssdm name="specinterface_ln0"/></StgValue>
</operation>

<operation id="17" st_id="1" stage="1" lat="1">
<core>NULL</core>
<MemPortIdVec></MemPortIdVec>
<condition id="-1">
<or_exp><and_exp></and_exp></or_exp>
</condition>

<Node id="25" bw="0" op_0_bw="0">
<![CDATA[
:12  br label %1

]]></Node>
<StgValue><ssdm name="br_ln232"/></StgValue>
</operation>
</state>

<state id="2" st_id="2">

<operation id="18" st_id="2" stage="1" lat="1">
<core>NULL</core>
<MemPortIdVec></MemPortIdVec>
<condition id="-1">
<or_exp><and_exp></and_exp></or_exp>
</condition>

<Node id="27" bw="9" op_0_bw="9" op_1_bw="0" op_2_bw="9" op_3_bw="0">
<![CDATA[
:0  %indvar_flatten = phi i9 [ 0, %0 ], [ %add_ln232, %ConcatLoopWidth ]

]]></Node>
<StgValue><ssdm name="indvar_flatten"/></StgValue>
</operation>

<operation id="19" st_id="2" stage="1" lat="1">
<core>Cmp</core>
<MemPortIdVec></MemPortIdVec>
<condition id="-1">
<or_exp><and_exp></and_exp></or_exp>
</condition>

<Node id="28" bw="1" op_0_bw="9" op_1_bw="9">
<![CDATA[
:1  %icmp_ln232 = icmp eq i9 %indvar_flatten, -256

]]></Node>
<StgValue><ssdm name="icmp_ln232"/></StgValue>
</operation>

<operation id="20" st_id="2" stage="1" lat="1">
<core>AddSub</core>
<MemPortIdVec></MemPortIdVec>
<condition id="-1">
<or_exp><and_exp></and_exp></or_exp>
</condition>

<Node id="29" bw="9" op_0_bw="9" op_1_bw="9">
<![CDATA[
:2  %add_ln232 = add i9 %indvar_flatten, 1

]]></Node>
<StgValue><ssdm name="add_ln232"/></StgValue>
</operation>

<operation id="21" st_id="2" stage="1" lat="1">
<core>NULL</core>
<MemPortIdVec></MemPortIdVec>
<condition id="-1">
<or_exp><and_exp></and_exp></or_exp>
</condition>

<Node id="30" bw="0" op_0_bw="1" op_1_bw="0" op_2_bw="0">
<![CDATA[
:3  br i1 %icmp_ln232, label %"concatenate3d_2<array<ap_fixed<16, 6, 5, 3, 0>, 3u>, array<ap_fixed<16, 6, 5, 3, 0>, 3u>, array<ap_fixed<16, 6, 5, 3, 0>, 6u>, config13>.exit", label %ConcatLoopWidth

]]></Node>
<StgValue><ssdm name="br_ln232"/></StgValue>
</operation>
</state>

<state id="3" st_id="3">

<operation id="22" st_id="3" stage="1" lat="1">
<core>NULL</core>
<MemPortIdVec></MemPortIdVec>
<condition id="-1">
<or_exp><and_exp><literal name="icmp_ln232" val="0"/>
</and_exp></or_exp>
</condition>

<Node id="32" bw="0" op_0_bw="0" op_1_bw="0">
<![CDATA[
ConcatLoopWidth:0  call void (...)* @_ssdm_op_SpecLoopName([33 x i8]* @ConcatLoopHeight_ConcatLoopWidth_str)

]]></Node>
<StgValue><ssdm name="specloopname_ln0"/></StgValue>
</operation>

<operation id="23" st_id="3" stage="1" lat="1">
<core>NULL</core>
<MemPortIdVec></MemPortIdVec>
<condition id="-1">
<or_exp><and_exp><literal name="icmp_ln232" val="0"/>
</and_exp></or_exp>
</condition>

<Node id="33" bw="32" op_0_bw="32" op_1_bw="64" op_2_bw="64" op_3_bw="64">
<![CDATA[
ConcatLoopWidth:1  %empty = call i32 (...)* @_ssdm_op_SpecLoopTripCount(i64 256, i64 256, i64 256)

]]></Node>
<StgValue><ssdm name="empty"/></StgValue>
</operation>

<operation id="24" st_id="3" stage="1" lat="1">
<core>NULL</core>
<MemPortIdVec></MemPortIdVec>
<condition id="-1">
<or_exp><and_exp><literal name="icmp_ln232" val="0"/>
</and_exp></or_exp>
</condition>

<Node id="34" bw="0" op_0_bw="0" op_1_bw="0">
<![CDATA[
ConcatLoopWidth:2  call void (...)* @_ssdm_op_SpecLoopName([16 x i8]* @p_str80) nounwind

]]></Node>
<StgValue><ssdm name="specloopname_ln234"/></StgValue>
</operation>

<operation id="25" st_id="3" stage="1" lat="1">
<core>NULL</core>
<MemPortIdVec></MemPortIdVec>
<condition id="-1">
<or_exp><and_exp><literal name="icmp_ln232" val="0"/>
</and_exp></or_exp>
</condition>

<Node id="35" bw="32" op_0_bw="32" op_1_bw="0">
<![CDATA[
ConcatLoopWidth:3  %tmp_95_i = call i32 (...)* @_ssdm_op_SpecRegionBegin([16 x i8]* @p_str80)

]]></Node>
<StgValue><ssdm name="tmp_95_i"/></StgValue>
</operation>

<operation id="26" st_id="3" stage="1" lat="1">
<core>NULL</core>
<MemPortIdVec></MemPortIdVec>
<condition id="-1">
<or_exp><and_exp><literal name="icmp_ln232" val="0"/>
</and_exp></or_exp>
</condition>

<Node id="36" bw="0" op_0_bw="0" op_1_bw="32" op_2_bw="32" op_3_bw="32" op_4_bw="32" op_5_bw="0">
<![CDATA[
ConcatLoopWidth:4  call void (...)* @_ssdm_op_SpecPipeline(i32 1, i32 1, i32 1, i32 0, [1 x i8]* @p_str20) nounwind

]]></Node>
<StgValue><ssdm name="specpipeline_ln235"/></StgValue>
</operation>

<operation id="27" st_id="3" stage="1" lat="1">
<core>FIFO</core>
<MemPortIdVec></MemPortIdVec>
<condition id="-1">
<or_exp><and_exp><literal name="icmp_ln232" val="0"/>
</and_exp></or_exp>
</condition>

<Node id="37" bw="48" op_0_bw="48" op_1_bw="16" op_2_bw="16" op_3_bw="16">
<![CDATA[
ConcatLoopWidth:5  %empty_230 = call { i16, i16, i16 } @_ssdm_op_Read.ap_fifo.volatile.i16P.i16P.i16P(i16* %data1_V_data_0_V, i16* %data1_V_data_1_V, i16* %data1_V_data_2_V)

]]></Node>
<StgValue><ssdm name="empty_230"/></StgValue>
</operation>

<operation id="28" st_id="3" stage="1" lat="1">
<core>NULL</core>
<MemPortIdVec></MemPortIdVec>
<condition id="-1">
<or_exp><and_exp><literal name="icmp_ln232" val="0"/>
</and_exp></or_exp>
</condition>

<Node id="38" bw="16" op_0_bw="48">
<![CDATA[
ConcatLoopWidth:6  %tmp_data_0_V = extractvalue { i16, i16, i16 } %empty_230, 0

]]></Node>
<StgValue><ssdm name="tmp_data_0_V"/></StgValue>
</operation>

<operation id="29" st_id="3" stage="1" lat="1">
<core>NULL</core>
<MemPortIdVec></MemPortIdVec>
<condition id="-1">
<or_exp><and_exp><literal name="icmp_ln232" val="0"/>
</and_exp></or_exp>
</condition>

<Node id="39" bw="16" op_0_bw="48">
<![CDATA[
ConcatLoopWidth:7  %tmp_data_1_V = extractvalue { i16, i16, i16 } %empty_230, 1

]]></Node>
<StgValue><ssdm name="tmp_data_1_V"/></StgValue>
</operation>

<operation id="30" st_id="3" stage="1" lat="1">
<core>NULL</core>
<MemPortIdVec></MemPortIdVec>
<condition id="-1">
<or_exp><and_exp><literal name="icmp_ln232" val="0"/>
</and_exp></or_exp>
</condition>

<Node id="40" bw="16" op_0_bw="48">
<![CDATA[
ConcatLoopWidth:8  %tmp_data_2_V = extractvalue { i16, i16, i16 } %empty_230, 2

]]></Node>
<StgValue><ssdm name="tmp_data_2_V"/></StgValue>
</operation>

<operation id="31" st_id="3" stage="1" lat="1">
<core>FIFO</core>
<MemPortIdVec></MemPortIdVec>
<condition id="-1">
<or_exp><and_exp><literal name="icmp_ln232" val="0"/>
</and_exp></or_exp>
</condition>

<Node id="41" bw="48" op_0_bw="48" op_1_bw="16" op_2_bw="16" op_3_bw="16">
<![CDATA[
ConcatLoopWidth:9  %empty_231 = call { i16, i16, i16 } @_ssdm_op_Read.ap_fifo.volatile.i16P.i16P.i16P(i16* %data2_V_data_0_V, i16* %data2_V_data_1_V, i16* %data2_V_data_2_V)

]]></Node>
<StgValue><ssdm name="empty_231"/></StgValue>
</operation>

<operation id="32" st_id="3" stage="1" lat="1">
<core>NULL</core>
<MemPortIdVec></MemPortIdVec>
<condition id="-1">
<or_exp><and_exp><literal name="icmp_ln232" val="0"/>
</and_exp></or_exp>
</condition>

<Node id="42" bw="16" op_0_bw="48">
<![CDATA[
ConcatLoopWidth:10  %tmp_data_0_V_31 = extractvalue { i16, i16, i16 } %empty_231, 0

]]></Node>
<StgValue><ssdm name="tmp_data_0_V_31"/></StgValue>
</operation>

<operation id="33" st_id="3" stage="1" lat="1">
<core>NULL</core>
<MemPortIdVec></MemPortIdVec>
<condition id="-1">
<or_exp><and_exp><literal name="icmp_ln232" val="0"/>
</and_exp></or_exp>
</condition>

<Node id="43" bw="16" op_0_bw="48">
<![CDATA[
ConcatLoopWidth:11  %tmp_data_1_V_30 = extractvalue { i16, i16, i16 } %empty_231, 1

]]></Node>
<StgValue><ssdm name="tmp_data_1_V_30"/></StgValue>
</operation>

<operation id="34" st_id="3" stage="1" lat="1">
<core>NULL</core>
<MemPortIdVec></MemPortIdVec>
<condition id="-1">
<or_exp><and_exp><literal name="icmp_ln232" val="0"/>
</and_exp></or_exp>
</condition>

<Node id="44" bw="16" op_0_bw="48">
<![CDATA[
ConcatLoopWidth:12  %tmp_data_2_V_30 = extractvalue { i16, i16, i16 } %empty_231, 2

]]></Node>
<StgValue><ssdm name="tmp_data_2_V_30"/></StgValue>
</operation>

<operation id="35" st_id="3" stage="1" lat="1">
<core>FIFO</core>
<MemPortIdVec></MemPortIdVec>
<condition id="-1">
<or_exp><and_exp><literal name="icmp_ln232" val="0"/>
</and_exp></or_exp>
</condition>

<Node id="45" bw="0" op_0_bw="0" op_1_bw="16" op_2_bw="16" op_3_bw="16" op_4_bw="16" op_5_bw="16" op_6_bw="16" op_7_bw="16" op_8_bw="16" op_9_bw="16" op_10_bw="16" op_11_bw="16" op_12_bw="16">
<![CDATA[
ConcatLoopWidth:13  call void @_ssdm_op_Write.ap_fifo.volatile.i16P.i16P.i16P.i16P.i16P.i16P(i16* %res_V_data_0_V, i16* %res_V_data_1_V, i16* %res_V_data_2_V, i16* %res_V_data_3_V, i16* %res_V_data_4_V, i16* %res_V_data_5_V, i16 %tmp_data_0_V, i16 %tmp_data_1_V, i16 %tmp_data_2_V, i16 %tmp_data_0_V_31, i16 %tmp_data_1_V_30, i16 %tmp_data_2_V_30)

]]></Node>
<StgValue><ssdm name="write_ln254"/></StgValue>
</operation>

<operation id="36" st_id="3" stage="1" lat="1">
<core>NULL</core>
<MemPortIdVec></MemPortIdVec>
<condition id="-1">
<or_exp><and_exp><literal name="icmp_ln232" val="0"/>
</and_exp></or_exp>
</condition>

<Node id="46" bw="32" op_0_bw="32" op_1_bw="0" op_2_bw="32">
<![CDATA[
ConcatLoopWidth:14  %empty_232 = call i32 (...)* @_ssdm_op_SpecRegionEnd([16 x i8]* @p_str80, i32 %tmp_95_i)

]]></Node>
<StgValue><ssdm name="empty_232"/></StgValue>
</operation>

<operation id="37" st_id="3" stage="1" lat="1">
<core>NULL</core>
<MemPortIdVec></MemPortIdVec>
<condition id="-1">
<or_exp><and_exp><literal name="icmp_ln232" val="0"/>
</and_exp></or_exp>
</condition>

<Node id="47" bw="0" op_0_bw="0">
<![CDATA[
ConcatLoopWidth:15  br label %1

]]></Node>
<StgValue><ssdm name="br_ln0"/></StgValue>
</operation>
</state>

<state id="4" st_id="4">

<operation id="38" st_id="4" stage="1" lat="1">
<core>NULL</core>
<MemPortIdVec></MemPortIdVec>
<condition id="-1">
<or_exp><and_exp></and_exp></or_exp>
</condition>

<Node id="49" bw="0">
<![CDATA[
concatenate3d_2<array<ap_fixed<16, 6, 5, 3, 0>, 3u>, array<ap_fixed<16, 6, 5, 3, 0>, 3u>, array<ap_fixed<16, 6, 5, 3, 0>, 6u>, config13>.exit:0  ret void

]]></Node>
<StgValue><ssdm name="ret_ln268"/></StgValue>
</operation>
</state>
</state_list>


<ports>
</ports>


<dataflows>
</dataflows>


</stg>
